Workbook

Sheet Read me
A1: BrandOS $1M ARR model (2026-10-26). Companion to docs/strategy/MILLION-DOLLAR-PLAN.md.
A2: Yellow cells on Inputs are assumptions. Change them and every other sheet recalculates.
A3: Source column: "measured" = from prod data (query id in the plan appendix); "guess" = no data yet, with the cheapest test to replace it.
A4: Month 0 = Nov 2026 (launch Nov 2). Target = $1,000,000 ARR = $83,333 MRR.
A5: Funnel per month: new scanned handles x signup rate x card rate x card-to-paid = new paying creators; paying creators decay by monthly churn.
A6: B2B (agency/brand) accounts are added separately per month at the Agency price, with their own churn.

Sheet Summary
A1: Scenario | B1: First month at $1M ARR | C1: MRR month 12 (Nov 2027) | D1: Paying creators month 12 | E1: B2B accounts month 12 | F1: Cumulative scanned handles needed by month 12
A2: Worst | B2: =IFERROR(INDEX(Worst!B2:B49,MATCH("YES",Worst!J2:J49,0)),"not within 4 years") | C2: =Worst!H14 | D2: =Worst!E14 | E2: =Worst!G14 | F2: =SUM(Worst!C2:C14)
A3: Expected | B3: =IFERROR(INDEX(Expected!B2:B49,MATCH("YES",Expected!J2:J49,0)),"not within 4 years") | C3: =Expected!H14 | D3: =Expected!E14 | E3: =Expected!G14 | F3: =SUM(Expected!C2:C14)
A4: Optimistic | B4: =IFERROR(INDEX(Optimistic!B2:B49,MATCH("YES",Optimistic!J2:J49,0)),"not within 4 years") | C4: =Optimistic!H14 | D4: =Optimistic!E14 | E4: =Optimistic!G14 | F4: =SUM(Optimistic!C2:C14)
A6: Members needed for $83,333 MRR (no churn assumed):
A7: All creators at $39 | B7: =ROUNDUP(83333/39,0)
A8: All creators at $29 | B8: =ROUNDUP(83333/29,0)
A9: Agencies only at $249 | B9: =ROUNDUP(83333/249,0)
A10: Mix: 1,500 creators @$39 + 100 Team @$99 + agencies @$249 for the rest | B10: =1500+100+ROUNDUP((83333-1500*39-100*99)/249,0)

Sheet Inputs
A1: Assumption | B1: Worst | C1: Expected | D1: Optimistic | E1: Unit | F1: Source | G1: Evidence / cheapest test to replace a guess
A2: Target ARR | B2: 1000000 | C2: 1000000 | D2: 1000000 | E2: $ | F2: definition
A3: New scanned handles, month 0 (Nov 2026) | B3: 1000 | C3: 2500 | D3: 5000 | E3: handles/mo | F3: guess | G3: Measured: Oct 1-26 = 217 handles (Q-C4); launch week Mar 16 = 4,105 (Q2). Test: count handles scanned Nov 2-30.
A4: Monthly growth in new handles | B4: 0.05 | C4: 0.12 | D4: 0.18 | E4: %/mo | F4: guess | G4: Test: Nov vs Dec handles. Driven by daily teardowns + reply waves (GTM plan).
A5: Scan -> email/account signup | B5: 0.12 | C5: 0.15 | D5: 0.21 | E5: % | F5: measured | G5: Launch week 883/4,105 = 21.5% (Q-C3); Oct 32/217 = 14.7% (Q-C4).
A6: Signup -> card on file | B6: 0.08 | C6: 0.15 | D6: 0.25 | E6: % | F6: guess | G6: No Stripe on prod yet (0 customers). Test: Founding 100 card adds by Nov 16 / signups since Nov 2.
A7: Card -> paid after free period | B7: 0.4 | C7: 0.5 | D7: 0.6 | E7: % | F7: guess | G7: Test: Dec 3 charges succeeded / cards on file. Opt-out card trials commonly convert 40-60% (benchmark, not BrandOS data).
A8: Creator monthly churn | B8: 0.12 | C8: 0.08 | D8: 0.05 | E8: %/mo | F8: guess | G8: Rescan proxy shows ~0% week-4 return pre-dashboard (Q-C1). Test: Jan 3 renewals.
A9: Creator ARPU | B9: 29 | C9: 35 | D9: 39 | E9: $/mo | F9: definition | G9: Founding 100 at $29 for life, then $39 (LAUNCH-PLAN). Blend depends on mix.
A10: New B2B (agency/brand) accounts, month 0 | B10: 0.5 | C10: 2 | D10: 5 | E10: accounts/mo | F10: guess | G10: Zero today. Test: 10 agency/brand conversations -> letters of intent by Dec 3.
A11: B2B monthly growth | B11: 0 | C11: 0.1 | D11: 0.15 | E11: %/mo | F11: guess
A12: B2B price | B12: 249 | C12: 249 | D12: 249 | E12: $/mo | F12: definition | G12: Agency plan (planned). Competitors: Favikon brand EUR159-499, Modash $199, HypeAuditor ~$299, Kaito Pro $833, KOL agencies ~$5K+.
A13: B2B monthly churn | B13: 0.05 | C13: 0.03 | D13: 0.02 | E13: %/mo | F13: guess
A14: Cost per scan (SocialData + Claude) | B14: 0.06 | C14: 0.04 | D14: 0.03 | E14: $/scan | F14: estimate | G14: From code: ~64 SocialData results x $0.0002 + Claude Haiku score + identity calls. Verify on invoices.
A15: Scans per paying member per month | B15: 12 | C15: 8 | D15: 6 | E15: scans/mo | F15: guess | G15: Dashboard rescans + compares. Test: avg scans per member in Nov.

Sheet Worst
A1: Month # | B1: Month | C1: New handles | D1: New paying creators | E1: Paying creators | F1: New B2B | G1: B2B accounts | H1: MRR | I1: ARR | J1: Hit $1M?
A2: 0 | B2: =EDATE(DATE(2026,11,1),A2) | C2: =Inputs!$B$3*(1+Inputs!$B$4)^A2 | D2: =C2*Inputs!$B$5*Inputs!$B$6*Inputs!$B$7 | E2: =0*(1-Inputs!$B$8)+D2 | F2: =Inputs!$B$10*(1+Inputs!$B$11)^A2 | G2: =0*(1-Inputs!$B$13)+F2 | H2: =E2*Inputs!$B$9+G2*Inputs!$B$12 | I2: =H2*12 | J2: =IF(I2>=Inputs!$B$2,"YES","")
A3: 1 | B3: =EDATE(DATE(2026,11,1),A3) | C3: =Inputs!$B$3*(1+Inputs!$B$4)^A3 | D3: =C3*Inputs!$B$5*Inputs!$B$6*Inputs!$B$7 | E3: =E2*(1-Inputs!$B$8)+D3 | F3: =Inputs!$B$10*(1+Inputs!$B$11)^A3 | G3: =G2*(1-Inputs!$B$13)+F3 | H3: =E3*Inputs!$B$9+G3*Inputs!$B$12 | I3: =H3*12 | J3: =IF(I3>=Inputs!$B$2,"YES","")
A4: 2 | B4: =EDATE(DATE(2026,11,1),A4) | C4: =Inputs!$B$3*(1+Inputs!$B$4)^A4 | D4: =C4*Inputs!$B$5*Inputs!$B$6*Inputs!$B$7 | E4: =E3*(1-Inputs!$B$8)+D4 | F4: =Inputs!$B$10*(1+Inputs!$B$11)^A4 | G4: =G3*(1-Inputs!$B$13)+F4 | H4: =E4*Inputs!$B$9+G4*Inputs!$B$12 | I4: =H4*12 | J4: =IF(I4>=Inputs!$B$2,"YES","")
A5: 3 | B5: =EDATE(DATE(2026,11,1),A5) | C5: =Inputs!$B$3*(1+Inputs!$B$4)^A5 | D5: =C5*Inputs!$B$5*Inputs!$B$6*Inputs!$B$7 | E5: =E4*(1-Inputs!$B$8)+D5 | F5: =Inputs!$B$10*(1+Inputs!$B$11)^A5 | G5: =G4*(1-Inputs!$B$13)+F5 | H5: =E5*Inputs!$B$9+G5*Inputs!$B$12 | I5: =H5*12 | J5: =IF(I5>=Inputs!$B$2,"YES","")
A6: 4 | B6: =EDATE(DATE(2026,11,1),A6) | C6: =Inputs!$B$3*(1+Inputs!$B$4)^A6 | D6: =C6*Inputs!$B$5*Inputs!$B$6*Inputs!$B$7 | E6: =E5*(1-Inputs!$B$8)+D6 | F6: =Inputs!$B$10*(1+Inputs!$B$11)^A6 | G6: =G5*(1-Inputs!$B$13)+F6 | H6: =E6*Inputs!$B$9+G6*Inputs!$B$12 | I6: =H6*12 | J6: =IF(I6>=Inputs!$B$2,"YES","")
A7: 5 | B7: =EDATE(DATE(2026,11,1),A7) | C7: =Inputs!$B$3*(1+Inputs!$B$4)^A7 | D7: =C7*Inputs!$B$5*Inputs!$B$6*Inputs!$B$7 | E7: =E6*(1-Inputs!$B$8)+D7 | F7: =Inputs!$B$10*(1+Inputs!$B$11)^A7 | G7: =G6*(1-Inputs!$B$13)+F7 | H7: =E7*Inputs!$B$9+G7*Inputs!$B$12 | I7: =H7*12 | J7: =IF(I7>=Inputs!$B$2,"YES","")
A8: 6 | B8: =EDATE(DATE(2026,11,1),A8) | C8: =Inputs!$B$3*(1+Inputs!$B$4)^A8 | D8: =C8*Inputs!$B$5*Inputs!$B$6*Inputs!$B$7 | E8: =E7*(1-Inputs!$B$8)+D8 | F8: =Inputs!$B$10*(1+Inputs!$B$11)^A8 | G8: =G7*(1-Inputs!$B$13)+F8 | H8: =E8*Inputs!$B$9+G8*Inputs!$B$12 | I8: =H8*12 | J8: =IF(I8>=Inputs!$B$2,"YES","")
A9: 7 | B9: =EDATE(DATE(2026,11,1),A9) | C9: =Inputs!$B$3*(1+Inputs!$B$4)^A9 | D9: =C9*Inputs!$B$5*Inputs!$B$6*Inputs!$B$7 | E9: =E8*(1-Inputs!$B$8)+D9 | F9: =Inputs!$B$10*(1+Inputs!$B$11)^A9 | G9: =G8*(1-Inputs!$B$13)+F9 | H9: =E9*Inputs!$B$9+G9*Inputs!$B$12 | I9: =H9*12 | J9: =IF(I9>=Inputs!$B$2,"YES","")
A10: 8 | B10: =EDATE(DATE(2026,11,1),A10) | C10: =Inputs!$B$3*(1+Inputs!$B$4)^A10 | D10: =C10*Inputs!$B$5*Inputs!$B$6*Inputs!$B$7 | E10: =E9*(1-Inputs!$B$8)+D10 | F10: =Inputs!$B$10*(1+Inputs!$B$11)^A10 | G10: =G9*(1-Inputs!$B$13)+F10 | H10: =E10*Inputs!$B$9+G10*Inputs!$B$12 | I10: =H10*12 | J10: =IF(I10>=Inputs!$B$2,"YES","")
A11: 9 | B11: =EDATE(DATE(2026,11,1),A11) | C11: =Inputs!$B$3*(1+Inputs!$B$4)^A11 | D11: =C11*Inputs!$B$5*Inputs!$B$6*Inputs!$B$7 | E11: =E10*(1-Inputs!$B$8)+D11 | F11: =Inputs!$B$10*(1+Inputs!$B$11)^A11 | G11: =G10*(1-Inputs!$B$13)+F11 | H11: =E11*Inputs!$B$9+G11*Inputs!$B$12 | I11: =H11*12 | J11: =IF(I11>=Inputs!$B$2,"YES","")
A12: 10 | B12: =EDATE(DATE(2026,11,1),A12) | C12: =Inputs!$B$3*(1+Inputs!$B$4)^A12 | D12: =C12*Inputs!$B$5*Inputs!$B$6*Inputs!$B$7 | E12: =E11*(1-Inputs!$B$8)+D12 | F12: =Inputs!$B$10*(1+Inputs!$B$11)^A12 | G12: =G11*(1-Inputs!$B$13)+F12 | H12: =E12*Inputs!$B$9+G12*Inputs!$B$12 | I12: =H12*12 | J12: =IF(I12>=Inputs!$B$2,"YES","")
A13: 11 | B13: =EDATE(DATE(2026,11,1),A13) | C13: =Inputs!$B$3*(1+Inputs!$B$4)^A13 | D13: =C13*Inputs!$B$5*Inputs!$B$6*Inputs!$B$7 | E13: =E12*(1-Inputs!$B$8)+D13 | F13: =Inputs!$B$10*(1+Inputs!$B$11)^A13 | G13: =G12*(1-Inputs!$B$13)+F13 | H13: =E13*Inputs!$B$9+G13*Inputs!$B$12 | I13: =H13*12 | J13: =IF(I13>=Inputs!$B$2,"YES","")
A14: 12 | B14: =EDATE(DATE(2026,11,1),A14) | C14: =Inputs!$B$3*(1+Inputs!$B$4)^A14 | D14: =C14*Inputs!$B$5*Inputs!$B$6*Inputs!$B$7 | E14: =E13*(1-Inputs!$B$8)+D14 | F14: =Inputs!$B$10*(1+Inputs!$B$11)^A14 | G14: =G13*(1-Inputs!$B$13)+F14 | H14: =E14*Inputs!$B$9+G14*Inputs!$B$12 | I14: =H14*12 | J14: =IF(I14>=Inputs!$B$2,"YES","")
... A49: 47 | B49: =EDATE(DATE(2026,11,1),A49) | C49: =Inputs!$B$3*(1+Inputs!$B$4)^A49 | D49: =C49*Inputs!$B$5*Inputs!$B$6*Inputs!$B$7 | E49: =E48*(1-Inputs!$B$8)+D49 | F49: =Inputs!$B$10*(1+Inputs!$B$11)^A49 | G49: =G48*(1-Inputs!$B$13)+F49 | H49: =E49*Inputs!$B$9+G49*Inputs!$B$12 | I49: =H49*12 | J49: =IF(I49>=Inputs!$B$2,"YES","")

Sheet Expected
A1: Month # | B1: Month | C1: New handles | D1: New paying creators | E1: Paying creators | F1: New B2B | G1: B2B accounts | H1: MRR | I1: ARR | J1: Hit $1M?
A2: 0 | B2: =EDATE(DATE(2026,11,1),A2) | C2: =Inputs!$C$3*(1+Inputs!$C$4)^A2 | D2: =C2*Inputs!$C$5*Inputs!$C$6*Inputs!$C$7 | E2: =0*(1-Inputs!$C$8)+D2 | F2: =Inputs!$C$10*(1+Inputs!$C$11)^A2 | G2: =0*(1-Inputs!$C$13)+F2 | H2: =E2*Inputs!$C$9+G2*Inputs!$C$12 | I2: =H2*12 | J2: =IF(I2>=Inputs!$C$2,"YES","")
A3: 1 | B3: =EDATE(DATE(2026,11,1),A3) | C3: =Inputs!$C$3*(1+Inputs!$C$4)^A3 | D3: =C3*Inputs!$C$5*Inputs!$C$6*Inputs!$C$7 | E3: =E2*(1-Inputs!$C$8)+D3 | F3: =Inputs!$C$10*(1+Inputs!$C$11)^A3 | G3: =G2*(1-Inputs!$C$13)+F3 | H3: =E3*Inputs!$C$9+G3*Inputs!$C$12 | I3: =H3*12 | J3: =IF(I3>=Inputs!$C$2,"YES","")
A4: 2 | B4: =EDATE(DATE(2026,11,1),A4) | C4: =Inputs!$C$3*(1+Inputs!$C$4)^A4 | D4: =C4*Inputs!$C$5*Inputs!$C$6*Inputs!$C$7 | E4: =E3*(1-Inputs!$C$8)+D4 | F4: =Inputs!$C$10*(1+Inputs!$C$11)^A4 | G4: =G3*(1-Inputs!$C$13)+F4 | H4: =E4*Inputs!$C$9+G4*Inputs!$C$12 | I4: =H4*12 | J4: =IF(I4>=Inputs!$C$2,"YES","")
A5: 3 | B5: =EDATE(DATE(2026,11,1),A5) | C5: =Inputs!$C$3*(1+Inputs!$C$4)^A5 | D5: =C5*Inputs!$C$5*Inputs!$C$6*Inputs!$C$7 | E5: =E4*(1-Inputs!$C$8)+D5 | F5: =Inputs!$C$10*(1+Inputs!$C$11)^A5 | G5: =G4*(1-Inputs!$C$13)+F5 | H5: =E5*Inputs!$C$9+G5*Inputs!$C$12 | I5: =H5*12 | J5: =IF(I5>=Inputs!$C$2,"YES","")
A6: 4 | B6: =EDATE(DATE(2026,11,1),A6) | C6: =Inputs!$C$3*(1+Inputs!$C$4)^A6 | D6: =C6*Inputs!$C$5*Inputs!$C$6*Inputs!$C$7 | E6: =E5*(1-Inputs!$C$8)+D6 | F6: =Inputs!$C$10*(1+Inputs!$C$11)^A6 | G6: =G5*(1-Inputs!$C$13)+F6 | H6: =E6*Inputs!$C$9+G6*Inputs!$C$12 | I6: =H6*12 | J6: =IF(I6>=Inputs!$C$2,"YES","")
A7: 5 | B7: =EDATE(DATE(2026,11,1),A7) | C7: =Inputs!$C$3*(1+Inputs!$C$4)^A7 | D7: =C7*Inputs!$C$5*Inputs!$C$6*Inputs!$C$7 | E7: =E6*(1-Inputs!$C$8)+D7 | F7: =Inputs!$C$10*(1+Inputs!$C$11)^A7 | G7: =G6*(1-Inputs!$C$13)+F7 | H7: =E7*Inputs!$C$9+G7*Inputs!$C$12 | I7: =H7*12 | J7: =IF(I7>=Inputs!$C$2,"YES","")
A8: 6 | B8: =EDATE(DATE(2026,11,1),A8) | C8: =Inputs!$C$3*(1+Inputs!$C$4)^A8 | D8: =C8*Inputs!$C$5*Inputs!$C$6*Inputs!$C$7 | E8: =E7*(1-Inputs!$C$8)+D8 | F8: =Inputs!$C$10*(1+Inputs!$C$11)^A8 | G8: =G7*(1-Inputs!$C$13)+F8 | H8: =E8*Inputs!$C$9+G8*Inputs!$C$12 | I8: =H8*12 | J8: =IF(I8>=Inputs!$C$2,"YES","")
A9: 7 | B9: =EDATE(DATE(2026,11,1),A9) | C9: =Inputs!$C$3*(1+Inputs!$C$4)^A9 | D9: =C9*Inputs!$C$5*Inputs!$C$6*Inputs!$C$7 | E9: =E8*(1-Inputs!$C$8)+D9 | F9: =Inputs!$C$10*(1+Inputs!$C$11)^A9 | G9: =G8*(1-Inputs!$C$13)+F9 | H9: =E9*Inputs!$C$9+G9*Inputs!$C$12 | I9: =H9*12 | J9: =IF(I9>=Inputs!$C$2,"YES","")
A10: 8 | B10: =EDATE(DATE(2026,11,1),A10) | C10: =Inputs!$C$3*(1+Inputs!$C$4)^A10 | D10: =C10*Inputs!$C$5*Inputs!$C$6*Inputs!$C$7 | E10: =E9*(1-Inputs!$C$8)+D10 | F10: =Inputs!$C$10*(1+Inputs!$C$11)^A10 | G10: =G9*(1-Inputs!$C$13)+F10 | H10: =E10*Inputs!$C$9+G10*Inputs!$C$12 | I10: =H10*12 | J10: =IF(I10>=Inputs!$C$2,"YES","")
A11: 9 | B11: =EDATE(DATE(2026,11,1),A11) | C11: =Inputs!$C$3*(1+Inputs!$C$4)^A11 | D11: =C11*Inputs!$C$5*Inputs!$C$6*Inputs!$C$7 | E11: =E10*(1-Inputs!$C$8)+D11 | F11: =Inputs!$C$10*(1+Inputs!$C$11)^A11 | G11: =G10*(1-Inputs!$C$13)+F11 | H11: =E11*Inputs!$C$9+G11*Inputs!$C$12 | I11: =H11*12 | J11: =IF(I11>=Inputs!$C$2,"YES","")
A12: 10 | B12: =EDATE(DATE(2026,11,1),A12) | C12: =Inputs!$C$3*(1+Inputs!$C$4)^A12 | D12: =C12*Inputs!$C$5*Inputs!$C$6*Inputs!$C$7 | E12: =E11*(1-Inputs!$C$8)+D12 | F12: =Inputs!$C$10*(1+Inputs!$C$11)^A12 | G12: =G11*(1-Inputs!$C$13)+F12 | H12: =E12*Inputs!$C$9+G12*Inputs!$C$12 | I12: =H12*12 | J12: =IF(I12>=Inputs!$C$2,"YES","")
A13: 11 | B13: =EDATE(DATE(2026,11,1),A13) | C13: =Inputs!$C$3*(1+Inputs!$C$4)^A13 | D13: =C13*Inputs!$C$5*Inputs!$C$6*Inputs!$C$7 | E13: =E12*(1-Inputs!$C$8)+D13 | F13: =Inputs!$C$10*(1+Inputs!$C$11)^A13 | G13: =G12*(1-Inputs!$C$13)+F13 | H13: =E13*Inputs!$C$9+G13*Inputs!$C$12 | I13: =H13*12 | J13: =IF(I13>=Inputs!$C$2,"YES","")
A14: 12 | B14: =EDATE(DATE(2026,11,1),A14) | C14: =Inputs!$C$3*(1+Inputs!$C$4)^A14 | D14: =C14*Inputs!$C$5*Inputs!$C$6*Inputs!$C$7 | E14: =E13*(1-Inputs!$C$8)+D14 | F14: =Inputs!$C$10*(1+Inputs!$C$11)^A14 | G14: =G13*(1-Inputs!$C$13)+F14 | H14: =E14*Inputs!$C$9+G14*Inputs!$C$12 | I14: =H14*12 | J14: =IF(I14>=Inputs!$C$2,"YES","")
... A49: 47 | B49: =EDATE(DATE(2026,11,1),A49) | C49: =Inputs!$C$3*(1+Inputs!$C$4)^A49 | D49: =C49*Inputs!$C$5*Inputs!$C$6*Inputs!$C$7 | E49: =E48*(1-Inputs!$C$8)+D49 | F49: =Inputs!$C$10*(1+Inputs!$C$11)^A49 | G49: =G48*(1-Inputs!$C$13)+F49 | H49: =E49*Inputs!$C$9+G49*Inputs!$C$12 | I49: =H49*12 | J49: =IF(I49>=Inputs!$C$2,"YES","")

Sheet Optimistic
A1: Month # | B1: Month | C1: New handles | D1: New paying creators | E1: Paying creators | F1: New B2B | G1: B2B accounts | H1: MRR | I1: ARR | J1: Hit $1M?
A2: 0 | B2: =EDATE(DATE(2026,11,1),A2) | C2: =Inputs!$D$3*(1+Inputs!$D$4)^A2 | D2: =C2*Inputs!$D$5*Inputs!$D$6*Inputs!$D$7 | E2: =0*(1-Inputs!$D$8)+D2 | F2: =Inputs!$D$10*(1+Inputs!$D$11)^A2 | G2: =0*(1-Inputs!$D$13)+F2 | H2: =E2*Inputs!$D$9+G2*Inputs!$D$12 | I2: =H2*12 | J2: =IF(I2>=Inputs!$D$2,"YES","")
A3: 1 | B3: =EDATE(DATE(2026,11,1),A3) | C3: =Inputs!$D$3*(1+Inputs!$D$4)^A3 | D3: =C3*Inputs!$D$5*Inputs!$D$6*Inputs!$D$7 | E3: =E2*(1-Inputs!$D$8)+D3 | F3: =Inputs!$D$10*(1+Inputs!$D$11)^A3 | G3: =G2*(1-Inputs!$D$13)+F3 | H3: =E3*Inputs!$D$9+G3*Inputs!$D$12 | I3: =H3*12 | J3: =IF(I3>=Inputs!$D$2,"YES","")
A4: 2 | B4: =EDATE(DATE(2026,11,1),A4) | C4: =Inputs!$D$3*(1+Inputs!$D$4)^A4 | D4: =C4*Inputs!$D$5*Inputs!$D$6*Inputs!$D$7 | E4: =E3*(1-Inputs!$D$8)+D4 | F4: =Inputs!$D$10*(1+Inputs!$D$11)^A4 | G4: =G3*(1-Inputs!$D$13)+F4 | H4: =E4*Inputs!$D$9+G4*Inputs!$D$12 | I4: =H4*12 | J4: =IF(I4>=Inputs!$D$2,"YES","")
A5: 3 | B5: =EDATE(DATE(2026,11,1),A5) | C5: =Inputs!$D$3*(1+Inputs!$D$4)^A5 | D5: =C5*Inputs!$D$5*Inputs!$D$6*Inputs!$D$7 | E5: =E4*(1-Inputs!$D$8)+D5 | F5: =Inputs!$D$10*(1+Inputs!$D$11)^A5 | G5: =G4*(1-Inputs!$D$13)+F5 | H5: =E5*Inputs!$D$9+G5*Inputs!$D$12 | I5: =H5*12 | J5: =IF(I5>=Inputs!$D$2,"YES","")
A6: 4 | B6: =EDATE(DATE(2026,11,1),A6) | C6: =Inputs!$D$3*(1+Inputs!$D$4)^A6 | D6: =C6*Inputs!$D$5*Inputs!$D$6*Inputs!$D$7 | E6: =E5*(1-Inputs!$D$8)+D6 | F6: =Inputs!$D$10*(1+Inputs!$D$11)^A6 | G6: =G5*(1-Inputs!$D$13)+F6 | H6: =E6*Inputs!$D$9+G6*Inputs!$D$12 | I6: =H6*12 | J6: =IF(I6>=Inputs!$D$2,"YES","")
A7: 5 | B7: =EDATE(DATE(2026,11,1),A7) | C7: =Inputs!$D$3*(1+Inputs!$D$4)^A7 | D7: =C7*Inputs!$D$5*Inputs!$D$6*Inputs!$D$7 | E7: =E6*(1-Inputs!$D$8)+D7 | F7: =Inputs!$D$10*(1+Inputs!$D$11)^A7 | G7: =G6*(1-Inputs!$D$13)+F7 | H7: =E7*Inputs!$D$9+G7*Inputs!$D$12 | I7: =H7*12 | J7: =IF(I7>=Inputs!$D$2,"YES","")
A8: 6 | B8: =EDATE(DATE(2026,11,1),A8) | C8: =Inputs!$D$3*(1+Inputs!$D$4)^A8 | D8: =C8*Inputs!$D$5*Inputs!$D$6*Inputs!$D$7 | E8: =E7*(1-Inputs!$D$8)+D8 | F8: =Inputs!$D$10*(1+Inputs!$D$11)^A8 | G8: =G7*(1-Inputs!$D$13)+F8 | H8: =E8*Inputs!$D$9+G8*Inputs!$D$12 | I8: =H8*12 | J8: =IF(I8>=Inputs!$D$2,"YES","")
A9: 7 | B9: =EDATE(DATE(2026,11,1),A9) | C9: =Inputs!$D$3*(1+Inputs!$D$4)^A9 | D9: =C9*Inputs!$D$5*Inputs!$D$6*Inputs!$D$7 | E9: =E8*(1-Inputs!$D$8)+D9 | F9: =Inputs!$D$10*(1+Inputs!$D$11)^A9 | G9: =G8*(1-Inputs!$D$13)+F9 | H9: =E9*Inputs!$D$9+G9*Inputs!$D$12 | I9: =H9*12 | J9: =IF(I9>=Inputs!$D$2,"YES","")
A10: 8 | B10: =EDATE(DATE(2026,11,1),A10) | C10: =Inputs!$D$3*(1+Inputs!$D$4)^A10 | D10: =C10*Inputs!$D$5*Inputs!$D$6*Inputs!$D$7 | E10: =E9*(1-Inputs!$D$8)+D10 | F10: =Inputs!$D$10*(1+Inputs!$D$11)^A10 | G10: =G9*(1-Inputs!$D$13)+F10 | H10: =E10*Inputs!$D$9+G10*Inputs!$D$12 | I10: =H10*12 | J10: =IF(I10>=Inputs!$D$2,"YES","")
A11: 9 | B11: =EDATE(DATE(2026,11,1),A11) | C11: =Inputs!$D$3*(1+Inputs!$D$4)^A11 | D11: =C11*Inputs!$D$5*Inputs!$D$6*Inputs!$D$7 | E11: =E10*(1-Inputs!$D$8)+D11 | F11: =Inputs!$D$10*(1+Inputs!$D$11)^A11 | G11: =G10*(1-Inputs!$D$13)+F11 | H11: =E11*Inputs!$D$9+G11*Inputs!$D$12 | I11: =H11*12 | J11: =IF(I11>=Inputs!$D$2,"YES","")
A12: 10 | B12: =EDATE(DATE(2026,11,1),A12) | C12: =Inputs!$D$3*(1+Inputs!$D$4)^A12 | D12: =C12*Inputs!$D$5*Inputs!$D$6*Inputs!$D$7 | E12: =E11*(1-Inputs!$D$8)+D12 | F12: =Inputs!$D$10*(1+Inputs!$D$11)^A12 | G12: =G11*(1-Inputs!$D$13)+F12 | H12: =E12*Inputs!$D$9+G12*Inputs!$D$12 | I12: =H12*12 | J12: =IF(I12>=Inputs!$D$2,"YES","")
A13: 11 | B13: =EDATE(DATE(2026,11,1),A13) | C13: =Inputs!$D$3*(1+Inputs!$D$4)^A13 | D13: =C13*Inputs!$D$5*Inputs!$D$6*Inputs!$D$7 | E13: =E12*(1-Inputs!$D$8)+D13 | F13: =Inputs!$D$10*(1+Inputs!$D$11)^A13 | G13: =G12*(1-Inputs!$D$13)+F13 | H13: =E13*Inputs!$D$9+G13*Inputs!$D$12 | I13: =H13*12 | J13: =IF(I13>=Inputs!$D$2,"YES","")
A14: 12 | B14: =EDATE(DATE(2026,11,1),A14) | C14: =Inputs!$D$3*(1+Inputs!$D$4)^A14 | D14: =C14*Inputs!$D$5*Inputs!$D$6*Inputs!$D$7 | E14: =E13*(1-Inputs!$D$8)+D14 | F14: =Inputs!$D$10*(1+Inputs!$D$11)^A14 | G14: =G13*(1-Inputs!$D$13)+F14 | H14: =E14*Inputs!$D$9+G14*Inputs!$D$12 | I14: =H14*12 | J14: =IF(I14>=Inputs!$D$2,"YES","")
... A49: 47 | B49: =EDATE(DATE(2026,11,1),A49) | C49: =Inputs!$D$3*(1+Inputs!$D$4)^A49 | D49: =C49*Inputs!$D$5*Inputs!$D$6*Inputs!$D$7 | E49: =E48*(1-Inputs!$D$8)+D49 | F49: =Inputs!$D$10*(1+Inputs!$D$11)^A49 | G49: =G48*(1-Inputs!$D$13)+F49 | H49: =E49*Inputs!$D$9+G49*Inputs!$D$12 | I49: =H49*12 | J49: =IF(I49>=Inputs!$D$2,"YES","")

Sheet Unit economics
A1: Metric | B1: Worst | C1: Expected | D1: Optimistic | E1: Note
A2: Creator ARPU ($/mo) | B2: =Inputs!$B$9 | C2: =Inputs!$C$9 | D2: =Inputs!$D$9
A3: Scan cost per member per month ($) | B3: =Inputs!$B$14*Inputs!$B$15 | C3: =Inputs!$C$14*Inputs!$C$15 | D3: =Inputs!$D$14*Inputs!$D$15 | E3: variable AI + data cost only
A4: Gross margin per creator | B4: =1-B3/B2 | C4: =1-C3/C2 | D4: =1-D3/D2
A5: Creator lifetime (months) = 1/churn | B5: =1/Inputs!$B$8 | C5: =1/Inputs!$C$8 | D5: =1/Inputs!$D$8
A6: Creator lifetime value ($) | B6: =B2*B4*B5 | C6: =C2*C4*C5 | D6: =D2*D4*D5 | E6: ARPU x margin x lifetime
A7: Cost of a free scan that never pays ($) | B7: =Inputs!$B$14 | C7: =Inputs!$C$14 | D7: =Inputs!$D$14
A8: Free scans paid for by one member (LTV / scan cost) | B8: =B6/B7 | C8: =C6/C7 | D8: =D6/D7 | E8: how many free scans one member funds
A9: B2B lifetime value ($) | B9: =Inputs!$B$12/Inputs!$B$13 | C9: =Inputs!$C$12/Inputs!$C$13 | D9: =Inputs!$D$12/Inputs!$D$13 | E9: price / churn, margin ~100% before support

Sheet Measured (prod)
A1: Metric | B1: Value | C1: Query id (see plan appendix) | D1: As of
A2: All-time scans | B2: 6756 | C2: Q1 | D2: 2026-10-26
A3: All-time unique handles scanned | B3: 4748 | C3: Q1 | D3: 2026-10-26
A4: Scans while signed in | B4: 9 | C4: Q1 | D4: 2026-10-26
A5: Launch week (Mar 16) scans / handles | B5: 5,459 / 4,105 | C5: Q2 | D5: 2026-10-26
A6: Launch week email signups | B6: 883 | C6: Q4 | D6: 2026-10-26
A7: Scan->signup, launch week | B7: 0.215 | C7: C3 | D7: 2026-10-26
A8: Oct 1-26 scans / handles / signups | B8: 285 / 217 / 32 | C8: C4 | D8: 2026-10-26
A9: Scan->signup, Oct | B9: 0.147 | C9: C4 | D9: 2026-10-26
A10: Email signups all-time (EmailSignup rows) | B10: 1022 | C10: tables | D10: 2026-10-26
A11: Accounts (User rows) | B11: 7 | C11: Q6 | D11: 2026-10-26
A12: Stripe customers / subscriptions on prod | B12: 0 | C12: Q6/Q7 (Stripe key not pullable; DB shows none) | D12: 2026-10-26
A13: Index reservations | B13: 1004 | C13: Q9 | D13: 2026-10-26
A14: Pricing poll votes | B14: 0 | C14: tables | D14: 2026-10-26
A15: Mar-16 signup cohort: rescanned in week 1 / 2 / 4 / 8 | B15: 8.9% / 0.8% / 0.3% / 0.2% | C15: C1 | D15: 2026-10-26
A16: Oct 22 email: recipients who rescanned by Oct 26 | B16: 78 / 1,004 (7.8%) | C16: C5 | D16: 2026-10-26
A17: Oct 22 email subject A vs B scan rate | B17: 9.4% vs 4.8% | C17: LAUNCH-PLAN.md | D17: 2026-10-26
A18: Resend: emails since Oct 7 / bounced | B18: 1,089 / ~2% | C18: Resend API (open tracking off: no open/click data) | D18: 2026-10-26
